ez_setup.py
aegis/__init__.py
aegis/aegis.py
aegis_latex-0.1.dist-info/LICENSE
aegis_latex-0.1.dist-info/METADATA
aegis_latex-0.1.dist-info/WHEEL
aegis_latex-0.1.dist-info/top_level.txt
aegis_latex-0.1.dist-info/RECORD
